fastllm/__init__.py
fastllm/cache.py
fastllm/core.py
fastllm/providers/__init__.py
fastllm/providers/base.py
fastllm/providers/openai.py
fastllm_kit-0.1.9.dist-info/METADATA
fastllm_kit-0.1.9.dist-info/WHEEL
fastllm_kit-0.1.9.dist-info/RECORD
