Metadata-Version: 2.4
Name: fastllm-kit
Version: 0.1.9
Summary: High-performance parallel LLM API request tool with caching and multiple provider support
Author-email: Daniil Larionov <rexhaif.io@gmail.com>
License: MIT
Keywords: ai,api,caching,llm,openai,parallel
Classifier: Development Status :: 4 - Beta
Classifier: Intended Audience :: Developers
Classifier: License :: OSI Approved :: MIT License
Classifier: Programming Language :: Python :: 3.9
Classifier: Programming Language :: Python :: 3.10
Classifier: Programming Language :: Python :: 3.11
Classifier: Topic :: Scientific/Engineering :: Artificial Intelligence
Classifier: Topic :: Software Development :: Libraries :: Python Modules
Requires-Python: >=3.9
Requires-Dist: anyio>=4.8.0
Requires-Dist: diskcache>=5.6.3
Requires-Dist: httpx>=0.27.2
Requires-Dist: nest-asyncio>=1.6.0
Requires-Dist: openai>=1.61.0
Requires-Dist: pydantic>=2.10.6
Requires-Dist: rich>=13.9.4
Requires-Dist: tqdm>=4.67.1
Requires-Dist: typing-extensions>=4.12.2
Requires-Dist: xxhash>=3.0.0
Provides-Extra: dev
Requires-Dist: black>=24.10.0; extra == 'dev'
Requires-Dist: coverage>=7.6.10; extra == 'dev'
Requires-Dist: dotenv>=0.9.9; extra == 'dev'
Requires-Dist: ipywidgets>=8.1.5; extra == 'dev'
Requires-Dist: numpy>=2.0.2; extra == 'dev'
Requires-Dist: pytest-asyncio>=0.23.8; extra == 'dev'
Requires-Dist: pytest-cov>=4.1.0; extra == 'dev'
Requires-Dist: pytest>=8.3.4; extra == 'dev'
Requires-Dist: ruff>=0.3.7; extra == 'dev'
Requires-Dist: typer>=0.15.2; extra == 'dev'
